awking.py
awking-1.1.2.dist-info/LICENSE
awking-1.1.2.dist-info/METADATA
awking-1.1.2.dist-info/WHEEL
awking-1.1.2.dist-info/top_level.txt
awking-1.1.2.dist-info/RECORD
