Metadata-Version: 2.1
Name: awking
Version: 1.1.2
Summary: Make it easier to use Python as an AWK replacement
Home-page: https://github.com/adsr303/awking
Author: Artur de Sousa Rocha
Author-email: adsr@poczta.onet.pl
License: MIT
Platform: UNKNOWN
Classifier: Intended Audience :: Developers
Classifier: Topic :: Text Processing
Classifier: License :: OSI Approved :: MIT License
Classifier: Programming Language :: Python :: 3
Classifier: Development Status :: 5 - Production/Stable
License-File: LICENSE
